oidc_auth/__init__.py
oidc_auth/authentication.py
oidc_auth/settings.py
oidc_auth/test.py
oidc_auth/util.py
drf_jwt_multi_auth-1.1.0.dist-info/METADATA
drf_jwt_multi_auth-1.1.0.dist-info/WHEEL
drf_jwt_multi_auth-1.1.0.dist-info/licenses/LICENSE
drf_jwt_multi_auth-1.1.0.dist-info/RECORD
