Metadata-Version: 2.4
Name: drf-jwt-multi-auth
Version: 1.1.0
Summary: Package for authenticating JWT tokens from multiple issuers
Project-URL: Homepage, https://github.com/Uninett/drf-oidc-auth
Project-URL: Issues, https://github.com/Uninett/drf-oidc-auth/issues
Author-email: "Simon O. Tveit" <simon.tveit@sikt.no>
License-Expression: MIT
License-File: LICENSE
Classifier: Operating System :: OS Independent
Classifier: Programming Language :: Python :: 3
Requires-Python: >=3.9
Requires-Dist: authlib>=0.15.0
Requires-Dist: cryptography>=2.6
Requires-Dist: django>=4.2.0
Requires-Dist: djangorestframework>=3.15.0
Requires-Dist: pyjwt>=2.6.0
Requires-Dist: requests>=2.20.0
